cogmitost/__init__.py
cogmitost/main.py
cogmitostream-1.0.0.dist-info/licenses/LICENSE
cogmitostream-1.0.0.dist-info/METADATA
cogmitostream-1.0.0.dist-info/WHEEL
cogmitostream-1.0.0.dist-info/top_level.txt
cogmitostream-1.0.0.dist-info/RECORD
