Metadata-Version: 2.4
Name: cogmitostream
Version: 1.0.0
Summary: Yayınlar için AI destekli otomatik konuşan bot
Home-page: https://github.com/senin-kendi-repo-urlin
Author: Aytunç Yalnız
Classifier: Programming Language :: Python :: 3
Classifier: Operating System :: OS Independent
Requires-Python: >=3.8
License-File: LICENSE
Requires-Dist: undetected-chromedriver
Requires-Dist: soundfile
Requires-Dist: soundcard
Requires-Dist: mtranslate
Requires-Dist: speechrecognition
Requires-Dist: ollama
Requires-Dist: customtkinter
Requires-Dist: python-telegram-bot
Requires-Dist: nest_asyncio
Requires-Dist: certifi
Dynamic: author
Dynamic: classifier
Dynamic: description
Dynamic: description-content-type
Dynamic: home-page
Dynamic: license-file
Dynamic: requires-dist
Dynamic: requires-python
Dynamic: summary
